coinespy/__init__.py
coinespy/__main__.py
coinespy/coines.py
coinespy/libcoines_64.dll
coinespy/libcoines_64.so
coinespy/libcoines_arm_64.dylib
coinespy/libcoines_i386_64.dylib
coinespy/libwinpthread-1.dll
coinespy/bin/x64/api-ms-win-core-console-l1-1-0.dll
coinespy/bin/x64/api-ms-win-core-console-l1-2-0.dll
coinespy/bin/x64/api-ms-win-core-datetime-l1-1-0.dll
coinespy/bin/x64/api-ms-win-core-debug-l1-1-0.dll
coinespy/bin/x64/api-ms-win-core-errorhandling-l1-1-0.dll
coinespy/bin/x64/api-ms-win-core-fibers-l1-1-0.dll
coinespy/bin/x64/api-ms-win-core-file-l1-1-0.dll
coinespy/bin/x64/api-ms-win-core-file-l1-2-0.dll
coinespy/bin/x64/api-ms-win-core-file-l2-1-0.dll
coinespy/bin/x64/api-ms-win-core-handle-l1-1-0.dll
coinespy/bin/x64/api-ms-win-core-heap-l1-1-0.dll
coinespy/bin/x64/api-ms-win-core-interlocked-l1-1-0.dll
coinespy/bin/x64/api-ms-win-core-libraryloader-l1-1-0.dll
coinespy/bin/x64/api-ms-win-core-localization-l1-2-0.dll
coinespy/bin/x64/api-ms-win-core-memory-l1-1-0.dll
coinespy/bin/x64/api-ms-win-core-namedpipe-l1-1-0.dll
coinespy/bin/x64/api-ms-win-core-processenvironment-l1-1-0.dll
coinespy/bin/x64/api-ms-win-core-processthreads-l1-1-0.dll
coinespy/bin/x64/api-ms-win-core-processthreads-l1-1-1.dll
coinespy/bin/x64/api-ms-win-core-profile-l1-1-0.dll
coinespy/bin/x64/api-ms-win-core-rtlsupport-l1-1-0.dll
coinespy/bin/x64/api-ms-win-core-string-l1-1-0.dll
coinespy/bin/x64/api-ms-win-core-synch-l1-1-0.dll
coinespy/bin/x64/api-ms-win-core-synch-l1-2-0.dll
coinespy/bin/x64/api-ms-win-core-sysinfo-l1-1-0.dll
coinespy/bin/x64/api-ms-win-core-timezone-l1-1-0.dll
coinespy/bin/x64/api-ms-win-core-util-l1-1-0.dll
coinespy/bin/x64/api-ms-win-crt-conio-l1-1-0.dll
coinespy/bin/x64/api-ms-win-crt-convert-l1-1-0.dll
coinespy/bin/x64/api-ms-win-crt-environment-l1-1-0.dll
coinespy/bin/x64/api-ms-win-crt-filesystem-l1-1-0.dll
coinespy/bin/x64/api-ms-win-crt-heap-l1-1-0.dll
coinespy/bin/x64/api-ms-win-crt-locale-l1-1-0.dll
coinespy/bin/x64/api-ms-win-crt-math-l1-1-0.dll
coinespy/tools/openocd/xpack-openocd-0.11.0-4/distro-info/CHANGELOG.md
coinespy/tools/openocd/xpack-openocd-0.11.0-4/distro-info/licenses/hidapi-hidapi-0.10.1/AUTHORS.txt
coinespy/tools/openocd/xpack-openocd-0.11.0-4/distro-info/licenses/hidapi-hidapi-0.10.1/LICENSE-bsd.txt
coinespy/tools/openocd/xpack-openocd-0.11.0-4/distro-info/licenses/hidapi-hidapi-0.10.1/LICENSE-gpl3.txt
coinespy/tools/openocd/xpack-openocd-0.11.0-4/distro-info/licenses/hidapi-hidapi-0.10.1/LICENSE-orig.txt
coinespy/tools/openocd/xpack-openocd-0.11.0-4/distro-info/licenses/hidapi-hidapi-0.10.1/LICENSE.txt
coinespy/tools/openocd/xpack-openocd-0.11.0-4/distro-info/licenses/hidapi-hidapi-0.10.1/README.md
coinespy/tools/openocd/xpack-openocd-0.11.0-4/distro-info/licenses/libftdi1-1.5/AUTHORS
coinespy/tools/openocd/xpack-openocd-0.11.0-4/distro-info/licenses/libftdi1-1.5/COPYING-CMAKE-SCRIPTS
coinespy/tools/openocd/xpack-openocd-0.11.0-4/distro-info/licenses/libftdi1-1.5/COPYING.GPL
coinespy/tools/openocd/xpack-openocd-0.11.0-4/distro-info/licenses/libftdi1-1.5/COPYING.LIB
coinespy/tools/openocd/xpack-openocd-0.11.0-4/distro-info/licenses/libftdi1-1.5/LICENSE
coinespy/tools/openocd/xpack-openocd-0.11.0-4/distro-info/licenses/libftdi1-1.5/README
coinespy/tools/openocd/xpack-openocd-0.11.0-4/distro-info/licenses/libftdi1-1.5/README.build
coinespy/tools/openocd/xpack-openocd-0.11.0-4/distro-info/licenses/libftdi1-1.5/README.mingw
coinespy/tools/openocd/xpack-openocd-0.11.0-4/distro-info/licenses/libiconv-1.16/AUTHORS
coinespy/tools/openocd/xpack-openocd-0.11.0-4/distro-info/licenses/libiconv-1.16/COPYING
coinespy/tools/openocd/xpack-openocd-0.11.0-4/distro-info/licenses/libiconv-1.16/COPYING.LIB
coinespy/tools/openocd/xpack-openocd-0.11.0-4/distro-info/licenses/libiconv-1.16/DEPENDENCIES
coinespy/tools/openocd/xpack-openocd-0.11.0-4/distro-info/licenses/libiconv-1.16/NEWS
coinespy/tools/openocd/xpack-openocd-0.11.0-4/distro-info/licenses/libiconv-1.16/README
coinespy/tools/openocd/xpack-openocd-0.11.0-4/distro-info/licenses/libiconv-1.16/THANKS
coinespy/tools/openocd/xpack-openocd-0.11.0-4/distro-info/licenses/libusb-1.0.24/AUTHORS
coinespy/tools/openocd/xpack-openocd-0.11.0-4/distro-info/licenses/libusb-1.0.24/COPYING
coinespy/tools/openocd/xpack-openocd-0.11.0-4/distro-info/licenses/libusb-1.0.24/NEWS
coinespy/tools/openocd/xpack-openocd-0.11.0-4/distro-info/licenses/libusb-1.0.24/README
coinespy/tools/openocd/xpack-openocd-0.11.0-4/distro-info/licenses/libusb-win32-src-1.2.6.0/AUTHORS.txt
coinespy/tools/openocd/xpack-openocd-0.11.0-4/distro-info/licenses/libusb-win32-src-1.2.6.0/COPYING_GPL.txt
coinespy/tools/openocd/xpack-openocd-0.11.0-4/distro-info/licenses/libusb-win32-src-1.2.6.0/COPYING_LGPL.txt
coinespy/tools/openocd/xpack-openocd-0.11.0-4/distro-info/licenses/libusb-win32-src-1.2.6.0/README.in
coinespy/tools/openocd/xpack-openocd-0.11.0-4/distro-info/licenses/libusb-win32-src-1.2.6.0/README.txt
coinespy/tools/openocd/xpack-openocd-0.11.0-4/distro-info/licenses/libusb-win32-src-1.2.6.0/libusb-win32-bin-README.txt.in
coinespy/tools/openocd/xpack-openocd-0.11.0-4/distro-info/licenses/openocd-0.11.0-4/AUTHORS
coinespy/tools/openocd/xpack-openocd-0.11.0-4/distro-info/licenses/openocd-0.11.0-4/AUTHORS.ChangeLog
coinespy/tools/openocd/xpack-openocd-0.11.0-4/distro-info/licenses/openocd-0.11.0-4/COPYING
coinespy/tools/openocd/xpack-openocd-0.11.0-4/distro-info/licenses/openocd-0.11.0-4/NEWS
coinespy/tools/openocd/xpack-openocd-0.11.0-4/distro-info/licenses/openocd-0.11.0-4/NEWS-0.10.0
coinespy/tools/openocd/xpack-openocd-0.11.0-4/distro-info/licenses/openocd-0.11.0-4/NEWS-0.11.0
coinespy/tools/openocd/xpack-openocd-0.11.0-4/distro-info/licenses/openocd-0.11.0-4/NEWS-0.2.0
coinespy/tools/openocd/xpack-openocd-0.11.0-4/distro-info/licenses/openocd-0.11.0-4/NEWS-0.3.0
coinespy/tools/openocd/xpack-openocd-0.11.0-4/distro-info/licenses/openocd-0.11.0-4/NEWS-0.4.0
coinespy/tools/openocd/xpack-openocd-0.11.0-4/distro-info/licenses/openocd-0.11.0-4/NEWS-0.5.0
