Metadata-Version: 2.4
Name: coinespy
Version: 1.0.6
Summary: Python wrapper for coinesAPI
Home-page: https://www.bosch-sensortec.com/
Author: Bosch Sensortec GmbH
Author-email: Bosch Sensortec GmbH <contact@bosch-sensortec.com>
Project-URL: Homepage, https://www.bosch-sensortec.com/
Project-URL: Source code, https://github.com/boschsensortec/COINES
Classifier: Programming Language :: Python :: 3
Classifier: Programming Language :: Python :: 2
Classifier: License :: OSI Approved :: BSD License
Classifier: Operating System :: Microsoft :: Windows
Classifier: Operating System :: POSIX :: Linux
Classifier: Operating System :: MacOS :: MacOS X
Requires-Python: >=2.6, <4
License-File: LICENSE.txt
Requires-Dist: flake8
Requires-Dist: lizard
Requires-Dist: pytest
Requires-Dist: pytest-cov
Requires-Dist: pytest-html
Dynamic: author
Dynamic: home-page
Dynamic: license-file
Dynamic: requires-python
